custom_function/__init__.py
custom_function/car_number.json
custom_function/car_number_tool.py
custom_function/common_tool.py
custom_function-1.0.3.dist-info/METADATA
custom_function-1.0.3.dist-info/WHEEL
custom_function-1.0.3.dist-info/top_level.txt
custom_function-1.0.3.dist-info/RECORD
