Metadata-Version: 2.1
Name: custom-function
Version: 1.0.3
Summary: 自用常用函数
Author: jlpersist
Author-email: jlpersist@163.com
Classifier: Programming Language :: Python :: 3
Classifier: License :: OSI Approved :: MIT License
Classifier: Operating System :: OS Independent
Requires-Python: >=3.10
Requires-Dist: rich
